LICENSE.txt
MANIFEST.in
README.rst
setup.py
sdt_metrics/__init__.py
sdt_metrics/_sdt_metrics.py
sdt_metrics/nonascii_fixer.py
sdt_metrics/sorted_ratio_enumerator.py
sdt_metrics.egg-info/PKG-INFO
sdt_metrics.egg-info/SOURCES.txt
sdt_metrics.egg-info/dependency_links.txt
sdt_metrics.egg-info/not-zip-safe
sdt_metrics.egg-info/top_level.txt
sdt_metrics/analysis/__init__.py
sdt_metrics/analysis/pairwise_comparison.py
sdt_metrics/analysis/scatter_matrices.py
sdt_metrics/analysis/loglinear_beta/loglinearbeta_analysis.py
sdt_metrics/analysis/loglinear_beta/pcolor_difference_plot.py
sdt_metrics/doc/build_metric_rst_files.py
sdt_metrics/doc/conf.py
sdt_metrics/plotting/__init__.py
sdt_metrics/plotting/_metric_validation_plot.py
sdt_metrics/plotting/_mult_roc_plot.py
sdt_metrics/plotting/_poc_plot.py
sdt_metrics/plotting/_roc_plot.py
sdt_metrics/support/__init__.py
sdt_metrics/support/singletonmixin.py
sdt_metrics/support/singletonmixin_test.py
sdt_metrics/tests/__init__.py
sdt_metrics/tests/test__sdt_metrics.py